loxprox/__init__.py
loxprox/colors.py
loxprox/config.py
loxprox/converter.py
loxprox/main.py
loxprox-0.1.1.dist-info/LICENSE
loxprox-0.1.1.dist-info/METADATA
loxprox-0.1.1.dist-info/WHEEL
loxprox-0.1.1.dist-info/entry_points.txt
loxprox-0.1.1.dist-info/top_level.txt
loxprox-0.1.1.dist-info/RECORD
